blackspammerbd/__init__.py
blackspammerbd/monitor.py
blackspammerbd_termux-1.0.1.dist-info/licenses/LICENSE
blackspammerbd_termux-1.0.1.dist-info/METADATA
blackspammerbd_termux-1.0.1.dist-info/WHEEL
blackspammerbd_termux-1.0.1.dist-info/entry_points.txt
blackspammerbd_termux-1.0.1.dist-info/top_level.txt
blackspammerbd_termux-1.0.1.dist-info/RECORD
